mujoco_py/__init__.py
mujoco_py/builder.py
mujoco_py/cymj.c
mujoco_py/cymj.pyx
mujoco_py/mjbatchrenderer.pyx
mujoco_py/mjpid.pyx
mujoco_py/mjrendercontext.pyx
mujoco_py/mjrenderpool.py
mujoco_py/mjsim.pyx
mujoco_py/mjsimstate.pyx
mujoco_py/mjviewer.py
mujoco_py/modder.py
mujoco_py/opengl_context.pyx
mujoco_py/utils.py
mujoco_py/version.py
mujoco_py/generated/__init__.py
mujoco_py/generated/const.py
mujoco_py/generated/cymj_2.1.2.15_311_linuxgpuextensionbuilder_311.so
mujoco_py/generated/cymj_2.1.2.15_313_linuxgpuextensionbuilder_313.so
mujoco_py/generated/wrappers.pxi
mujoco_py/gl/__init__.py
mujoco_py/gl/dummyshim.c
mujoco_py/gl/egl.h
mujoco_py/gl/eglext.h
mujoco_py/gl/eglplatform.h
mujoco_py/gl/eglshim.c
mujoco_py/gl/glshim.h
mujoco_py/gl/khrplatform.h
mujoco_py/gl/osmesashim.c
mujoco_py/pxd/__init__.py
mujoco_py/pxd/mjdata.pxd
mujoco_py/pxd/mjmodel.pxd
mujoco_py/pxd/mjrender.pxd
mujoco_py/pxd/mjui.pxd
mujoco_py/pxd/mjvisualize.pxd
mujoco_py/pxd/mujoco.pxd
mujoco_py/tests/__init__.py
mujoco_py/tests/include.xml
mujoco_py/tests/test.xml
mujoco_py/tests/test_composite.py
mujoco_py/tests/test_cymj.py
mujoco_py/tests/test_examples.py
mujoco_py/tests/test_gen_wrappers.py
mujoco_py/tests/test_modder.py
mujoco_py/tests/test_opengl_context.py
mujoco_py/tests/test_pid.py
mujoco_py/tests/test_render_pool.py
mujoco_py/tests/test_substep.py
mujoco_py/tests/test_vfs.py
mujoco_py/tests/test_viewer.py
mujoco_py/tests/utils.py
mujoco_py_cython3-2.1.2.15.dist-info/licenses/LICENSE.md
mujoco_py_cython3-2.1.2.15.dist-info/METADATA
mujoco_py_cython3-2.1.2.15.dist-info/WHEEL
mujoco_py_cython3-2.1.2.15.dist-info/top_level.txt
mujoco_py_cython3-2.1.2.15.dist-info/RECORD
