Metadata-Version: 2.4
Name: mujoco-py-cython3
Version: 2.1.2.15
Home-page: https://github.com/Kallinteris-Andreas/mujoco-py
Author: Kallinteris
Author-email: kallinteris@protonmai.com
Classifier: Programming Language :: Python :: 3
Classifier: Programming Language :: Python :: 3.6
Classifier: Programming Language :: Python :: 3.7
Classifier: Programming Language :: Python :: 3 :: Only
Requires-Python: >=3.6
License-File: LICENSE.md
Requires-Dist: glfw>=1.4.0
Requires-Dist: numpy>=1.11
Requires-Dist: Cython>=0.27.2
Requires-Dist: imageio>=2.1.2
Requires-Dist: cffi>=1.10
Requires-Dist: fasteners~=0.15
Dynamic: author
Dynamic: author-email
Dynamic: classifier
Dynamic: home-page
Dynamic: license-file
Dynamic: requires-dist
Dynamic: requires-python
